zope.tales-6.0-py3.11-nspkg.pth
zope/tales/__init__.py
zope/tales/engine.py
zope/tales/expressions.py
zope/tales/interfaces.py
zope/tales/pythonexpr.py
zope/tales/tales.py
zope/tales/tests/__init__.py
zope/tales/tests/simpleexpr.py
zope/tales/tests/test_expressions.py
zope/tales/tests/test_pythonexpr.py
zope/tales/tests/test_tales.py
zope/tales/tests/test_traverser.py
zope.tales-6.0.dist-info/LICENSE.txt
zope.tales-6.0.dist-info/METADATA
zope.tales-6.0.dist-info/WHEEL
zope.tales-6.0.dist-info/namespace_packages.txt
zope.tales-6.0.dist-info/top_level.txt
zope.tales-6.0.dist-info/RECORD
