Metadata-Version: 2.1
Name: zope.tales
Version: 6.0
Summary: Zope Template Application Language Expression Syntax (TALES)
Home-page: https://github.com/zopefoundation/zope.tales
Author: Zope Foundation and Contributors
Author-email: zope-dev@zope.dev
License: ZPL 2.1
Project-URL: Documentation, https://zopetales.readthedocs.io/
Project-URL: Issue Tracker, https://github.com/zopefoundation/zope.tales/issues
Project-URL: Sources, https://github.com/zopefoundation/zope.tales
Keywords: zope template xml tales
Classifier: Development Status :: 5 - Production/Stable
Classifier: Environment :: Web Environment
Classifier: Intended Audience :: Developers
Classifier: License :: OSI Approved :: Zope Public License
Classifier: Programming Language :: Python
Classifier: Programming Language :: Python :: 3
Classifier: Programming Language :: Python :: 3.7
Classifier: Programming Language :: Python :: 3.8
Classifier: Programming Language :: Python :: 3.9
Classifier: Programming Language :: Python :: 3.10
Classifier: Programming Language :: Python :: 3.11
Classifier: Programming Language :: Python :: Implementation :: CPython
Classifier: Programming Language :: Python :: Implementation :: PyPy
Classifier: Natural Language :: English
Classifier: Operating System :: OS Independent
Classifier: Topic :: Internet :: WWW/HTTP
Classifier: Framework :: Zope :: 3
Classifier: Framework :: Zope :: 5
Requires-Python: >=3.7
Provides-Extra: test
Provides-Extra: tal
Provides-Extra: docs
License-File: LICENSE.txt
